enerpy/__init__.py
enerpy/_api.py
enerpy/_types.py
EnerPy-1.1.0.dist-info/LICENSE
EnerPy-1.1.0.dist-info/METADATA
EnerPy-1.1.0.dist-info/WHEEL
EnerPy-1.1.0.dist-info/top_level.txt
EnerPy-1.1.0.dist-info/RECORD
