Metadata-Version: 2.1
Name: EnerPy
Version: 1.1.0
Summary: Python Wrapper for the Energy Information Administration (EIA) API
Home-page: https://gitlab.com/mpca-adau/enerpy
Author: Daniel Sullivan
Author-email: daniel.sullivan@state.mn.us
License: Lesser General Public License V3
Platform: UNKNOWN
Classifier: Programming Language :: Python :: 3
Classifier: License :: OSI Approved :: GNU Lesser General Public License v3 or later (LGPLv3+)
Classifier: Development Status :: 3 - Alpha
Classifier: Topic :: Software Development :: Libraries
Requires-Python: >3.6
Requires-Dist: requests
Requires-Dist: logger-mixin
Requires-Dist: pandas
